mdmodels_core-0.2.7.dist-info/METADATA
mdmodels_core-0.2.7.dist-info/WHEEL
mdmodels_core-0.2.7.dist-info/licenses/LICENSE.md
mdmodels_core/__init__.py
mdmodels_core/mdmodels_core.cpython-38-aarch64-linux-gnu.so
mdmodels_core-0.2.7.dist-info/RECORD
