Metadata-Version: 2.4
Name: mdmodels_core
Version: 0.2.7
Classifier: Programming Language :: Rust
Classifier: Programming Language :: Python :: Implementation :: CPython
Classifier: Programming Language :: Python :: Implementation :: PyPy
License-File: LICENSE.md
Summary: A tool to generate models, code and schemas from markdown files
Requires-Python: >=3.8
